{"raw": {"ivs_0": 0, "ability_0": 0, "level_0": 37, "species_id_0": 45, "move_1_0": 202, "move_2_0": 78, "move_3_0": 409, "move_4_0": 213, "ballseal_0": 0, "ivs_1": 0, "ability_1": 0, "level_1": 37, "species_id_1": 71, "move_1_1": 202, "move_2_1": 79, "move_3_1": 188, "move_4_1": 182, "ballseal_1": 0}, "readable": {"ivs_0": 0, "ability_0": 0, "level_0": 37, "species_id_0": "Vileplume", "move_1_0": "Giga Drain", "move_2_0": "Stun Spore", "move_3_0": "Drain Punch", "move_4_0": "Attract", "ballseal_0": 0, "ivs_1": 0, "ability_1": 0, "level_1": 37, "species_id_1": "Victreebel", "move_1_1": "Giga Drain", "move_2_1": "Sleep Powder", "move_3_1": "Sludge Bomb", "move_4_1": "Protect", "ballseal_1": 0, "count": 2, "form_0": 1, "form_1": 1, "template": 1}}