{"raw": {"base_hp": 75, "base_atk": 98, "base_def": 63, "base_speed": 101, "base_spatk": 98, "base_spdef": 63, "type_1": 9, "type_2": 9, "catchrate": 75, "stage": 2, "evs": 128, "item_1": 155, "item_2": 185, "item_3": 0, "gender": 31, "hatch_cycle": 20, "base_happy": 70, "exp_rate": 0, "egg_group_1": 5, "egg_group_2": 5, "ability_1": 82, "ability_2": 0, "ability_3": 66, "flee": 0, "form_id": 0, "form": 0, "num_forms": 1, "color": 0, "base_exp": 174, "height": 10, "weight": 280, "tm_1-32": 3425783329, "tm_33-64": 881524580, "tm_65-95+hm_1": 2724495371, "hm_2-6": 0, "tutors": 0}, "readable": {"base_hp": 75, "base_atk": 98, "base_def": 63, "base_speed": 101, "base_spatk": 98, "base_spdef": 63, "type_1": "Fire", "type_2": "Fire", "catchrate": 75, "stage": 2, "evs": 128, "item_1": "Oran Berry", "item_2": "Passho Berry", "item_3": "None", "gender": 31, "hatch_cycle": 20, "base_happy": 70, "exp_rate": "Medium Fast", "egg_group_1": "Field", "egg_group_2": "Field", "ability_1": "GLUTTONY", "ability_2": "", "ability_3": "BLAZE", "flee": 0, "form_id": 0, "form": 0, "num_forms": 1, "color": 0, "base_exp": 174, "height": 10, "weight": 280, "tm_1-32": 3425783329, "tm_33-64": 881524580, "tm_65-95+hm_1": 2724495371, "hm_2-6": 0, "tutors": 0, "index": 514, "gen": "5", "name": "SIMISEAR", "hp_yield": 0, "atk_yield": 0, "def_yield": 0, "speed_yield": 2, "spatk_yield": 0, "spdef_yield": 0}}