{"raw": {"effect": 4, "category": 1, "power": 80, "type": 10, "accuracy": 100, "pp": 15, "effect_chance": 30, "target": 8, "priority": 0, "properties": 50, "contest_effect": 17, "contest_type": 4}, "readable": {"effect": "Chance to Burn", "category": "Special", "power": 80, "type": "Fire", "accuracy": 100, "pp": 15, "effect_chance": 30, "target": 8, "priority": 0, "properties": 50, "contest_effect": 17, "contest_type": 4, "index": 436, "animation": 436, "name": "Lava Plume", "contact": 0, "blocked_by_protect": 1, "reflected_by_magic_coat": 0, "stolen_by_snatch": 0, "copied_by_mirror_move": 1, "kings_rock": 1, "keep_hp_bar": 0, "hide_shadow": 0}}