{"raw": {"effect": 44, "category": 0, "power": 50, "type": 8, "accuracy": 85, "pp": 15, "effect_chance": 0, "target": 0, "priority": 0, "properties": 115, "contest_effect": 0, "contest_type": 0}, "readable": {"effect": "Hits twice", "category": "Physical", "power": 50, "type": "Steel", "accuracy": 85, "pp": 15, "effect_chance": 0, "target": 0, "priority": 0, "properties": 115, "contest_effect": 0, "contest_type": 0, "index": 547, "animation": 547, "name": "Gear Grind", "contact": 1, "blocked_by_protect": 1, "reflected_by_magic_coat": 0, "stolen_by_snatch": 0, "copied_by_mirror_move": 1, "kings_rock": 1, "keep_hp_bar": 1, "hide_shadow": 0}}