{"raw": {"move_id_0": 423, "lvl_learned_0": 1, "move_id_1": 424, "lvl_learned_1": 1, "move_id_2": 422, "lvl_learned_2": 1, "move_id_3": 17, "lvl_learned_3": 1, "move_id_4": 48, "lvl_learned_4": 1, "move_id_5": 44, "lvl_learned_5": 1, "move_id_6": 184, "lvl_learned_6": 1, "move_id_7": 46, "lvl_learned_7": 9, "move_id_8": 97, "lvl_learned_8": 17, "move_id_9": 246, "lvl_learned_9": 25, "move_id_10": 242, "lvl_learned_10": 33, "move_id_11": 36, "lvl_learned_11": 41, "move_id_12": 507, "lvl_learned_12": 49, "move_id_13": 442, "lvl_learned_13": 57, "move_id_14": 63, "lvl_learned_14": 65, "move_id_15": 157, "lvl_learned_15": 73, "move_id_16": 349, "lvl_learned_16": 81, "move_id_17": 457, "lvl_learned_17": 89, "move_id_18": 416, "lvl_learned_18": 97}, "readable": {"move_id_0": "ICE FANG", "lvl_learned_0": 1, "move_id_1": "FIRE FANG", "lvl_learned_1": 1, "move_id_2": "THUNDER FANG", "lvl_learned_2": 1, "move_id_3": "WING ATTACK", "lvl_learned_3": 1, "move_id_4": "SUPERSONIC", "lvl_learned_4": 1, "move_id_5": "BITE", "lvl_learned_5": 1, "move_id_6": "SCARY FACE", "lvl_learned_6": 1, "move_id_7": "ROAR", "lvl_learned_7": 9, "move_id_8": "AGILITY", "lvl_learned_8": 17, "move_id_9": "ANCIENTPOWER", "lvl_learned_9": 25, "move_id_10": "CRUNCH", "lvl_learned_10": 33, "move_id_11": "TAKE DOWN", "lvl_learned_11": 41, "move_id_12": "SKY DROP", "lvl_learned_12": 49, "move_id_13": "IRON HEAD", "lvl_learned_13": 57, "move_id_14": "HYPER BEAM", "lvl_learned_14": 65, "move_id_15": "ROCK SLIDE", "lvl_learned_15": 73, "move_id_16": "DRAGON DANCE", "lvl_learned_16": 81, "move_id_17": "HEAD SMASH", "lvl_learned_17": 89, "move_id_18": "GIGA IMPACT", "lvl_learned_18": 97, "index": 142, "move_id_0_index": 423, "move_id_1_index": 424, "move_id_2_index": 422, "move_id_3_index": 17, "move_id_4_index": 48, "move_id_5_index": 44, "move_id_6_index": 184, "move_id_7_index": 46, "move_id_8_index": 97, "move_id_9_index": 246, "move_id_10_index": 242, "move_id_11_index": 36, "move_id_12_index": 507, "move_id_13_index": 442, "move_id_14_index": 63, "move_id_15_index": 157, "move_id_16_index": 349, "move_id_17_index": 457, "move_id_18_index": 416}}