{"raw": {"base_hp": 255, "base_atk": 10, "base_def": 10, "base_speed": 55, "base_spatk": 75, "base_spdef": 135, "type_1": 0, "type_2": 0, "catchrate": 30, "stage": 3, "evs": 3, "item_1": 231, "item_2": 231, "item_3": 0, "gender": 254, "hatch_cycle": 40, "base_happy": 140, "exp_rate": 4, "egg_group_1": 6, "egg_group_2": 6, "ability_1": 30, "ability_2": 32, "ability_3": 131, "flee": 0, "form_id": 0, "form": 0, "num_forms": 1, "color": 9, "base_exp": 608, "height": 15, "weight": 468}, "readable": {"base_hp": 255, "base_atk": 10, "base_def": 10, "base_speed": 55, "base_spatk": 75, "base_spdef": 135, "type_1": "Normal", "type_2": "Normal", "catchrate": 30, "stage": 3, "evs": 3, "item_1": "Lucky Egg", "item_2": "Lucky Egg", "item_3": "None", "gender": 254, "hatch_cycle": 40, "base_happy": 140, "exp_rate": "Fast", "egg_group_1": "Fairy", "egg_group_2": "Fairy", "ability_1": "NATURAL CURE", "ability_2": "SERENE GRACE", "ability_3": "HEALER", "flee": 0, "form_id": 0, "form": 0, "num_forms": 1, "color": 9, "base_exp": 608, "height": 15, "weight": 468, "index": 242, "gen": "2", "name": "BLISSEY", "hp_yield": 1, "atk_yield": 0, "def_yield": 0, "speed_yield": 0, "spatk_yield": 0, "spdef_yield": 0}}