{"raw": {"base_hp": 101, "base_atk": 72, "base_def": 72, "base_speed": 29, "base_spatk": 99, "base_spdef": 89, "type_1": 9, "type_2": 9, "catchrate": 140, "base_exp": 162, "evs": 2, "item_1": 0, "item_2": 0, "gender": 127, "hatch_cycle": 20, "base_happy": 70, "exp_rate": 0, "egg_group_1": 6, "egg_group_2": 6, "ability_1": 131, "ability_2": 0, "flee": 0, "color": 9, "tm_1-32": 2492712488, "tm_33-64": 51420929, "tm_65-95+hm_1": 240529960, "hm_2-6": 0}, "readable": {"base_hp": 101, "base_atk": 72, "base_def": 72, "base_speed": 29, "base_spatk": 99, "base_spdef": 89, "type_1": "Mystery", "type_2": "Mystery", "catchrate": 140, "base_exp": 162, "evs": 2, "item_1": "None", "item_2": "None", "gender": 127, "hatch_cycle": 20, "base_happy": 70, "exp_rate": "Medium Fast", "egg_group_1": "Fairy", "egg_group_2": "Fairy", "ability_1": "HEALER", "ability_2": " -", "flee": 0, "color": 9, "tm_1-32": 2492712488, "tm_33-64": 51420929, "tm_65-95+hm_1": 240529960, "hm_2-6": 0, "index": 733, "gen": "6", "name": "Aromatisse", "hp_yield": 2, "atk_yield": 0, "def_yield": 0, "speed_yield": 0, "spatk_yield": 0, "spdef_yield": 0}}