{"raw": {"base_hp": 57, "base_atk": 80, "base_def": 91, "base_speed": 75, "base_spatk": 80, "base_spdef": 87, "type_1": 8, "type_2": 9, "catchrate": 75, "base_exp": 165, "evs": 16, "item_1": 0, "item_2": 0, "gender": 127, "hatch_cycle": 20, "base_happy": 70, "exp_rate": 4, "egg_group_1": 10, "egg_group_2": 10, "ability_1": 158, "ability_2": 0, "flee": 0, "color": 135, "tm_1-32": 0, "tm_33-64": 0, "tm_65-95+hm_1": 0, "hm_2-6": 0}, "readable": {"base_hp": 57, "base_atk": 80, "base_def": 91, "base_speed": 75, "base_spatk": 80, "base_spdef": 87, "type_1": "Steel", "type_2": "Mystery", "catchrate": 75, "base_exp": 165, "evs": 16, "item_1": "None", "item_2": "None", "gender": 127, "hatch_cycle": 20, "base_happy": 70, "exp_rate": "Fast", "egg_group_1": "Mineral", "egg_group_2": "Mineral", "ability_1": "PRANKSTER", "ability_2": " -", "flee": 0, "color": 135, "tm_1-32": 0, "tm_33-64": 0, "tm_65-95+hm_1": 0, "hm_2-6": 0, "index": 757, "gen": "6", "name": "Klefki", "hp_yield": 0, "atk_yield": 0, "def_yield": 1, "speed_yield": 0, "spatk_yield": 0, "spdef_yield": 0}}