{"raw": {"ivs_0": 0, "ability_0": 0, "level_0": 35, "padding_0": 0, "species_id_0": 53, "form_0": 0, "ivs_1": 0, "ability_1": 0, "level_1": 35, "padding_1": 0, "species_id_1": 51, "form_1": 0, "ivs_2": 0, "ability_2": 0, "level_2": 35, "padding_2": 0, "species_id_2": 496, "form_2": 0}, "readable": {"ivs_0": 0, "ability_0": 0, "level_0": 35, "padding_0": 0, "species_id_0": "PERSIAN", "form_0": 0, "ivs_1": 0, "ability_1": 0, "level_1": 35, "padding_1": 0, "species_id_1": "DUGTRIO", "form_1": 0, "ivs_2": 0, "ability_2": 0, "level_2": 35, "padding_2": 0, "species_id_2": "SERVINE", "form_2": 0, "count": 3, "gender_0": "Default", "gender_1": "Default", "gender_2": "Default", "template": 0}}