{"raw": {"ivs_0": 250, "ability_0": 1, "level_0": 88, "padding_0": 0, "species_id_0": 78, "form_0": 0, "ivs_1": 250, "ability_1": 2, "level_1": 88, "padding_1": 0, "species_id_1": 395, "form_1": 0, "ivs_2": 250, "ability_2": 2, "level_2": 88, "padding_2": 0, "species_id_2": 428, "form_2": 0, "ivs_3": 250, "ability_3": 2, "level_3": 88, "padding_3": 0, "species_id_3": 478, "form_3": 0, "ivs_4": 250, "ability_4": 2, "level_4": 88, "padding_4": 0, "species_id_4": 421, "form_4": 0, "ivs_5": 250, "ability_5": 1, "level_5": 88, "padding_5": 0, "species_id_5": 417, "form_5": 0}, "readable": {"ivs_0": 250, "ability_0": 0, "level_0": 88, "padding_0": 0, "species_id_0": "RAPIDASH", "form_0": 0, "ivs_1": 250, "ability_1": 0, "level_1": 88, "padding_1": 0, "species_id_1": "EMPOLEON", "form_1": 0, "ivs_2": 250, "ability_2": 0, "level_2": 88, "padding_2": 0, "species_id_2": "LOPUNNY", "form_2": 0, "ivs_3": 250, "ability_3": 0, "level_3": 88, "padding_3": 0, "species_id_3": "FROSLASS", "form_3": 0, "ivs_4": 250, "ability_4": 0, "level_4": 88, "padding_4": 0, "species_id_4": "CHERRIM", "form_4": 0, "ivs_5": 250, "ability_5": 0, "level_5": 88, "padding_5": 0, "species_id_5": "PACHIRISU", "form_5": 0, "count": 6, "gender_0": "Female", "gender_1": "Male", "gender_2": "Male", "gender_3": "Male", "gender_4": "Male", "gender_5": "Female", "template": 0}}