{"raw": {"move_id_0": 7, "lvl_learned_0": 1, "move_id_1": 33, "lvl_learned_1": 1, "move_id_2": 45, "lvl_learned_2": 1, "move_id_3": 86, "lvl_learned_3": 1, "move_id_4": 84, "lvl_learned_4": 1, "move_id_5": 86, "lvl_learned_5": 4, "move_id_6": 84, "lvl_learned_6": 8, "move_id_7": 178, "lvl_learned_7": 11, "move_id_8": 268, "lvl_learned_8": 16, "move_id_9": 36, "lvl_learned_9": 20, "move_id_10": 486, "lvl_learned_10": 25, "move_id_11": 109, "lvl_learned_11": 29, "move_id_12": 9, "lvl_learned_12": 30, "move_id_13": 408, "lvl_learned_13": 35, "move_id_14": 435, "lvl_learned_14": 40, "move_id_15": 538, "lvl_learned_15": 46, "move_id_16": 324, "lvl_learned_16": 51, "move_id_17": 113, "lvl_learned_17": 57, "move_id_18": 87, "lvl_learned_18": 62}, "readable": {"move_id_0": "FIRE PUNCH", "lvl_learned_0": 1, "move_id_1": "TACKLE", "lvl_learned_1": 1, "move_id_2": "GROWL", "lvl_learned_2": 1, "move_id_3": "THUNDER WAVE", "lvl_learned_3": 1, "move_id_4": "THUNDERSHOCK", "lvl_learned_4": 1, "move_id_5": "THUNDER WAVE", "lvl_learned_5": 4, "move_id_6": "THUNDERSHOCK", "lvl_learned_6": 8, "move_id_7": "COTTON SPORE", "lvl_learned_7": 11, "move_id_8": "CHARGE", "lvl_learned_8": 16, "move_id_9": "TAKE DOWN", "lvl_learned_9": 20, "move_id_10": "ELECTRO BALL", "lvl_learned_10": 25, "move_id_11": "CONFUSE RAY", "lvl_learned_11": 29, "move_id_12": "THUNDERPUNCH", "lvl_learned_12": 30, "move_id_13": "POWER GEM", "lvl_learned_13": 35, "move_id_14": "DISCHARGE", "lvl_learned_14": 40, "move_id_15": "COTTON GUARD", "lvl_learned_15": 46, "move_id_16": "SIGNAL BEAM", "lvl_learned_16": 51, "move_id_17": "LIGHT SCREEN", "lvl_learned_17": 57, "move_id_18": "THUNDER", "lvl_learned_18": 62, "index": 181, "move_id_0_index": 7, "move_id_1_index": 33, "move_id_2_index": 45, "move_id_3_index": 86, "move_id_4_index": 84, "move_id_5_index": 86, "move_id_6_index": 84, "move_id_7_index": 178, "move_id_8_index": 268, "move_id_9_index": 36, "move_id_10_index": 486, "move_id_11_index": 109, "move_id_12_index": 9, "move_id_13_index": 408, "move_id_14_index": 435, "move_id_15_index": 538, "move_id_16_index": 324, "move_id_17_index": 113, "move_id_18_index": 87}}