{"raw": {"move_id_0": 20, "lvl_learned_0": 1, "move_id_1": 420, "lvl_learned_1": 5, "move_id_2": 159, "lvl_learned_2": 9, "move_id_3": 229, "lvl_learned_3": 13, "move_id_4": 196, "lvl_learned_4": 17, "move_id_5": 54, "lvl_learned_5": 21, "move_id_6": 114, "lvl_learned_6": 21, "move_id_7": 62, "lvl_learned_7": 25, "move_id_8": 151, "lvl_learned_8": 29, "move_id_9": 58, "lvl_learned_9": 33, "move_id_10": 113, "lvl_learned_10": 37, "move_id_11": 115, "lvl_learned_11": 37, "move_id_12": 163, "lvl_learned_12": 41, "move_id_13": 109, "lvl_learned_13": 45, "move_id_14": 105, "lvl_learned_14": 49, "move_id_15": 76, "lvl_learned_15": 53, "move_id_16": 400, "lvl_learned_16": 57, "move_id_17": 329, "lvl_learned_17": 61}, "readable": {"move_id_0": "BIND", "lvl_learned_0": 1, "move_id_1": "ICE SHARD", "lvl_learned_1": 5, "move_id_2": "SHARPEN", "lvl_learned_2": 9, "move_id_3": "RAPID SPIN", "lvl_learned_3": 13, "move_id_4": "ICY WIND", "lvl_learned_4": 17, "move_id_5": "MIST", "lvl_learned_5": 21, "move_id_6": "HAZE", "lvl_learned_6": 21, "move_id_7": "AURORA BEAM", "lvl_learned_7": 25, "move_id_8": "ACID ARMOR", "lvl_learned_8": 29, "move_id_9": "ICE BEAM", "lvl_learned_9": 33, "move_id_10": "LIGHT SCREEN", "lvl_learned_10": 37, "move_id_11": "REFLECT", "lvl_learned_11": 37, "move_id_12": "SLASH", "lvl_learned_12": 41, "move_id_13": "CONFUSE RAY", "lvl_learned_13": 45, "move_id_14": "RECOVER", "lvl_learned_14": 49, "move_id_15": "SOLARBEAM", "lvl_learned_15": 53, "move_id_16": "NIGHT SLASH", "lvl_learned_16": 57, "move_id_17": "SHEER COLD", "lvl_learned_17": 61, "index": 615, "move_id_0_index": 20, "move_id_1_index": 420, "move_id_2_index": 159, "move_id_3_index": 229, "move_id_4_index": 196, "move_id_5_index": 54, "move_id_6_index": 114, "move_id_7_index": 62, "move_id_8_index": 151, "move_id_9_index": 58, "move_id_10_index": 113, "move_id_11_index": 115, "move_id_12_index": 163, "move_id_13_index": 109, "move_id_14_index": 105, "move_id_15_index": 76, "move_id_16_index": 400, "move_id_17_index": 329}}